[
  {
    "elements": [
      {
        "id": ";",
        "keyword": "Scenario",
        "line": 4,
        "name": "",
        "steps": [
          {
            "arguments": [],
            "keyword": "Given ",
            "line": 3,
            "match": {
              "location": "support/js/env.js:7"
            },
            "name": "this step fails",
            "result": {
              "duration": 19,
              "error_message": "Error: this step failed\n    at World.<anonymous> (/Users/aslakhellesoy/git/cucumber/cucumber-json-formatter/support/js/env.js:8:12)",
              "status": "failed"
            }
          },
          {
            "arguments": [],
            "keyword": "Given ",
            "line": 5,
            "match": {
              "location": "support/js/env.js:3"
            },
            "name": "this step passes",
            "result": {
              "status": "skipped"
            }
          }
        ],
        "tags": [],
        "type": "scenario"
      }
    ],
    "id": "",
    "keyword": "Feature",
    "line": 1,
    "name": "",
    "tags": [],
    "uri": "features/004-failing-background-step.feature"
  }
]
